adestis_netbox_certificate_management/__init__.py
adestis_netbox_certificate_management/apps.py
adestis_netbox_certificate_management/jobs.py
adestis_netbox_certificate_management/navigation.py
adestis_netbox_certificate_management/test.py
adestis_netbox_certificate_management/urls.py
adestis_netbox_certificate_management/api/__init__.py
adestis_netbox_certificate_management/api/urls.py
adestis_netbox_certificate_management/api/views.py
adestis_netbox_certificate_management/api/serializers/__init__.py
adestis_netbox_certificate_management/api/serializers/certificate_serializers.py
adestis_netbox_certificate_management/filtersets/__init__.py
adestis_netbox_certificate_management/filtersets/certificate.py
adestis_netbox_certificate_management/forms/__init__.py
adestis_netbox_certificate_management/forms/certificate.py
adestis_netbox_certificate_management/migrations/0001_initial.py
adestis_netbox_certificate_management/migrations/0002_remove_certificate_predecessor_certificate_and_more.py
adestis_netbox_certificate_management/migrations/0003_remove_certificate_custom_field_data_and_more.py
adestis_netbox_certificate_management/migrations/0004_alter_certificate_options_and_more.py
adestis_netbox_certificate_management/migrations/__init__.py
adestis_netbox_certificate_management/models/__init__.py
adestis_netbox_certificate_management/models/certificate.py
adestis_netbox_certificate_management/tables/__init__.py
adestis_netbox_certificate_management/tables/certificate.py
adestis_netbox_certificate_management/templates/adestis_netbox_certificate_management/application.html
adestis_netbox_certificate_management/templates/adestis_netbox_certificate_management/assign_application.html
adestis_netbox_certificate_management/templates/adestis_netbox_certificate_management/assign_cluster.html
adestis_netbox_certificate_management/templates/adestis_netbox_certificate_management/assign_cluster_group.html
adestis_netbox_certificate_management-1.0.20.dist-info/LICENSE
adestis_netbox_certificate_management-1.0.20.dist-info/METADATA
adestis_netbox_certificate_management-1.0.20.dist-info/WHEEL
adestis_netbox_certificate_management-1.0.20.dist-info/top_level.txt
adestis_netbox_certificate_management-1.0.20.dist-info/RECORD
