Metadata-Version: 2.1
Name: adestis-netbox-certificate-management
Version: 1.0.20
Summary: ADESTIS Certificate Management
Home-page: https://github.com/an-adestis/ADESTIS-Netbox-Certificate-Management
Author: ADESTIS GmbH
Author-email: pypi@adestis.de
License: GPL-3.0-only
Keywords: netbox,netbox-plugin,plugin
License-File: LICENSE
Requires-Dist: adestis-netbox-applications
Requires-Dist: cert-utils
Requires-Dist: josepy
